catio/__init__.py
catio/__main__.py
catio/_version.py
catio-0.1a1.dist-info/LICENSE
catio-0.1a1.dist-info/METADATA
catio-0.1a1.dist-info/WHEEL
catio-0.1a1.dist-info/entry_points.txt
catio-0.1a1.dist-info/top_level.txt
catio-0.1a1.dist-info/RECORD
